stree/Splitter.py
stree/Strees.py
stree/__init__.py
stree/_version.py
stree/tests/Snode_test.py
stree/tests/Splitter_test.py
stree/tests/Stree_test.py
stree/tests/__init__.py
stree/tests/utils.py
stree-1.4.0.dist-info/METADATA
stree-1.4.0.dist-info/WHEEL
stree-1.4.0.dist-info/licenses/LICENSE
stree-1.4.0.dist-info/RECORD
