Metadata-Version: 2.3
Name: STree
Version: 1.4.0
Summary: Oblique decision tree with svm nodes.
Project-URL: Code, https://github.com/Doctorado-ML/STree
Project-URL: Documentation, https://stree.readthedocs.io/en/latest/index.html
Author-email: Ricardo Montañana <ricardo.montanana@alu.uclm.es>
License: MIT License
License-File: LICENSE
Keywords: decision-tree,oblique-classifier,oblique-decision-tree,scikit-learn,svc,svm
Classifier: Development Status :: 5 - Production/Stable
Classifier: Intended Audience :: Developers
Classifier: Intended Audience :: Science/Research
Classifier: License :: OSI Approved :: MIT License
Classifier: Natural Language :: English
Classifier: Operating System :: OS Independent
Classifier: Programming Language :: Python :: 3.11
Classifier: Programming Language :: Python :: 3.12
Classifier: Topic :: Scientific/Engineering
Classifier: Topic :: Software Development
Requires-Python: >=3.11
Requires-Dist: mufs
Requires-Dist: scikit-learn>1.0
Provides-Extra: dev
Requires-Dist: black; extra == 'dev'
Requires-Dist: coverage; extra == 'dev'
Requires-Dist: flake8; extra == 'dev'
Requires-Dist: hatch; extra == 'dev'
Requires-Dist: pip-audit; extra == 'dev'
Provides-Extra: doc
Requires-Dist: myst-parser; extra == 'doc'
Requires-Dist: sphinx; extra == 'doc'
Requires-Dist: sphinx-autodoc-typehints; extra == 'doc'
Requires-Dist: sphinx-rtd-theme; extra == 'doc'
